kececisquares/__init__.py
kececisquares/_version.py
kececisquares/kececisquares.py
kececisquares-0.1.6.dist-info/licenses/LICENSE
kececisquares-0.1.6.dist-info/METADATA
kececisquares-0.1.6.dist-info/WHEEL
kececisquares-0.1.6.dist-info/top_level.txt
kececisquares-0.1.6.dist-info/RECORD
