Metadata-Version: 2.4
Name: kececisquares
Version: 0.1.6
Summary: Keçeci Binomial Squares (Keçeci Binom Kareleri): The Keçeci Binomial Square is a series of binomial coefficients forming a square region within Khayyam (مثلث خیام), Pascal, Binomial Triangle, selected from a specified starting row with defined size and alignment.
Home-page: https://github.com/WhiteSymmetry/kececisquares
Author: Mehmet Keçeci
Author-email: Mehmet Keçeci <mkececi@yaani.com>
Maintainer: Mehmet Keçeci
Maintainer-email: mkececi@yaani.com
License: MIT License
Project-URL: Homepage, https://github.com/WhiteSymmetry/kececisquares
Project-URL: Bug Tracker, https://github.com/WhiteSymmetry/kececisquares/issues
Classifier: Programming Language :: Python :: 3
Classifier: License :: OSI Approved :: MIT License
Classifier: Operating System :: OS Independent
Classifier: Intended Audience :: Science/Research
Classifier: Topic :: Scientific/Engineering :: Visualization
Requires-Python: >=3.10
License-File: LICENSE
Requires-Dist: matplotlib
Requires-Dist: numpy
Provides-Extra: test
Requires-Dist: pytest; extra == "test"
Requires-Dist: pytest-cov; extra == "test"
Requires-Dist: pytest-mock; extra == "test"
Requires-Dist: ruff; extra == "test"
Dynamic: author
Dynamic: home-page
Dynamic: license-file
Dynamic: maintainer
Dynamic: maintainer-email
Dynamic: requires-python
